mydm/__init__.py
mydm/bot.py
mydm/cqcode.py
mydm/event.py
mydm/exceptions.py
mydm/interactor/__init__.py
mydm/message.py
mydm/type.py
mydm/utils.py
mydm-0.0.4.dist-info/LICENSE
mydm-0.0.4.dist-info/METADATA
mydm-0.0.4.dist-info/WHEEL
mydm-0.0.4.dist-info/RECORD
