Metadata-Version: 2.1
Name: mydm
Version: 0.0.4
Summary: 一个使用OneBot v11/12协议的机器人框架
Home-page: https://github.com/yuyi2439/MyDM
License: MIT
Author: yuyi2439
Author-email: yuyi2439@qq.com
Requires-Python: >=3.10,<4.0
Classifier: License :: OSI Approved :: MIT License
Classifier: Programming Language :: Python :: 3
Classifier: Programming Language :: Python :: 3.10
Classifier: Programming Language :: Python :: 3.11
Provides-Extra: all
Requires-Dist: aiohttp (>=3.8.5,<4.0.0)
Requires-Dist: ujson (>=5.8.0,<6.0.0) ; extra == "all"
Project-URL: Repository, https://github.com/yuyi2439/MyDM
